rosdl/__init__.py
rosdl/addition.py
rosdl/cli.py
rosdl/data_generator.py
rosdl/eda_drift_module.py
rosdl/file_converter.py
rosdl/image_tools.py
rosdl/metadata_extractor.py
rosdl/ocr_module.py
rosdl/pdf_tools.py
rosdl/text_utils_module.py
rosdl-0.0.2.dist-info/licenses/LICENSE
rosdl-0.0.2.dist-info/METADATA
rosdl-0.0.2.dist-info/WHEEL
rosdl-0.0.2.dist-info/entry_points.txt
rosdl-0.0.2.dist-info/top_level.txt
rosdl-0.0.2.dist-info/RECORD
