Metadata-Version: 2.4
Name: rosdl
Version: 0.0.2
Summary: Research Oriented Smart Data Library (CLI + PDF/Math utilities)
Author-email: Joshua Dcosta <joshua04dcosta@gmail.com>
License: MIT
Project-URL: Homepage, https://github.com/joshua04d/rosdl
Project-URL: Documentation, https://github.com/joshua04d/rosdl#readme
Keywords: data,pdf,ai,ml,cli,math
Classifier: Programming Language :: Python :: 3
Classifier: License :: OSI Approved :: MIT License
Classifier: Operating System :: OS Independent
Requires-Python: >=3.11
License-File: LICENSE
Requires-Dist: click
Provides-Extra: mat
Requires-Dist: numpy; extra == "mat"
Provides-Extra: pdf
Requires-Dist: PyPDF2; extra == "pdf"
Requires-Dist: pdf2image; extra == "pdf"
Requires-Dist: Pillow; extra == "pdf"
Provides-Extra: ocr
Requires-Dist: pytesseract; extra == "ocr"
Requires-Dist: Pillow; extra == "ocr"
Provides-Extra: meta
Requires-Dist: python-magic; extra == "meta"
Requires-Dist: Pillow; extra == "meta"
Requires-Dist: mutagen; extra == "meta"
Requires-Dist: PyPDF2; extra == "meta"
Dynamic: license-file
